aurora_ai/__init__.py
aurora_ai/aurora_ai.pyc
aurora_ai-8.0.0.dist-info/METADATA
aurora_ai-8.0.0.dist-info/WHEEL
aurora_ai-8.0.0.dist-info/top_level.txt
aurora_ai-8.0.0.dist-info/RECORD
