Metadata-Version: 2.1
Name: aurora_ai
Version: 8.0.0
Summary: Advanced transcription model for audio and video files.
Author: Your Name
Author-email: your_email@example.com
Classifier: Programming Language :: Python :: 3
Classifier: License :: OSI Approved :: MIT License
Classifier: Operating System :: OS Independent
Requires-Python: >=3.7
